{
  "schema": "obs_prime.market_wiki_entry.v1",
  "market_id": "551085aee77989729e1416d0",
  "slug": "arcane_barrier",
  "market_slug": "arcane_barrier",
  "name_en": "Arcane Barrier",
  "name_en_slug": "arcane_barrier",
  "name_kr": "아케인 배리어",
  "aliases": [
    "Arcane Barrier",
    "arcane barrier",
    "arcane_barrier",
    "아케인 배리어"
  ],
  "tags": [
    "arcane_enhancement",
    "legendary"
  ],
  "game_ref": "/Lotus/Upgrades/CosmeticEnhancers/Defensive/InstantShieldOnDamage",
  "max_rank": 5,
  "tradable": true,
  "icon": "items/images/en/arcane_barrier.c4b3b25fcc9c874a4bfc0f8998b9f5bd.png",
  "thumb": "items/images/en/thumbs/arcane_barrier.c4b3b25fcc9c874a4bfc0f8998b9f5bd.128x128.png",
  "source": {
    "warframe_market_items": "https://api.warframe.market/v2/items"
  },
  "updated_at": "2026-06-28T15:19:32Z",
  "version": "26-06-29"
}