{
  "schema": "obs_prime.market_wiki_entry.v1",
  "market_id": "5615432cb66f8371035bfa33",
  "slug": "cataclysmic_continuum",
  "market_slug": "cataclysmic_continuum",
  "name_en": "Cataclysmic Continuum",
  "name_en_slug": "cataclysmic_continuum",
  "name_kr": "카타클리즈믹 컨티뉴엄",
  "aliases": [
    "Cataclysmic Continuum",
    "cataclysmic continuum",
    "cataclysmic_continuum",
    "카타클리즈믹 컨티뉴엄"
  ],
  "tags": [
    "augment",
    "limbo",
    "mod",
    "rare",
    "warframe"
  ],
  "game_ref": "/Lotus/Powersuits/Magician/TearInSpaceAugmentCard",
  "max_rank": 3,
  "tradable": true,
  "icon": "items/images/en/cataclysmic_continuum.97b3de0d31396da2b920bef226ea8791.png",
  "thumb": "items/images/en/thumbs/cataclysmic_continuum.97b3de0d31396da2b920bef226ea8791.128x128.png",
  "source": {
    "warframe_market_items": "https://api.warframe.market/v2/items"
  },
  "updated_at": "2026-06-28T15:19:32Z",
  "version": "26-06-29"
}