{
  "schema": "obs_prime.market_wiki_entry.v1",
  "market_id": "59e91860f25be4e10d36571d",
  "slug": "furax_wraith_blueprint",
  "market_slug": "furax_wraith_blueprint",
  "name_en": "Furax Wraith Blueprint",
  "name_en_slug": "furax_wraith_blueprint",
  "name_kr": "퓨랙스 레이스 설계도",
  "aliases": [
    "Furax Wraith",
    "Furax Wraith Blueprint",
    "furax wraith blueprint",
    "furax_wraith_blueprint",
    "퓨랙스 레이스",
    "퓨랙스 레이스 설계도"
  ],
  "tags": [
    "blueprint",
    "melee",
    "weapon"
  ],
  "game_ref": "/Lotus/Types/Recipes/Weapons/FuraxWraithBlueprint",
  "max_rank": null,
  "tradable": true,
  "icon": "items/images/en/furax_wraith_blueprint.c460830e1437c5ab3cd37e2ea51b09a9.png",
  "thumb": "items/images/en/thumbs/furax_wraith_blueprint.c460830e1437c5ab3cd37e2ea51b09a9.128x128.png",
  "source": {
    "warframe_market_items": "https://api.warframe.market/v2/items"
  },
  "updated_at": "2026-06-28T15:19:32Z",
  "version": "26-06-29"
}