{
  "schema": "obs_prime.market_wiki_entry.v1",
  "market_id": "5dff6e111456970316674a15",
  "slug": "predator",
  "market_slug": "predator",
  "name_en": "Predator",
  "name_en_slug": "predator",
  "name_kr": "프레데터",
  "aliases": [
    "Predator",
    "predator",
    "프레데터"
  ],
  "tags": [
    "mod",
    "railjack",
    "uncommon"
  ],
  "game_ref": "/Lotus/Upgrades/Mods/Railjack/Gunnery/VidarGunnerWeaponCritChance",
  "max_rank": 5,
  "tradable": true,
  "icon": "items/images/en/predator.00d9a614bca0ce0b665e89d76de93023.png",
  "thumb": "items/images/en/thumbs/predator.00d9a614bca0ce0b665e89d76de93023.128x128.png",
  "source": {
    "warframe_market_items": "https://api.warframe.market/v2/items"
  },
  "updated_at": "2026-06-28T15:19:32Z",
  "version": "26-06-29"
}