{
  "schema": "obs_prime.market_wiki_entry.v1",
  "market_id": "55a4693be779890222824cef",
  "slug": "seeking_fury",
  "market_slug": "seeking_fury",
  "name_en": "Seeking Fury",
  "name_en_slug": "seeking_fury",
  "name_kr": "시킹 퓨리",
  "aliases": [
    "Seeking Fury",
    "seeking fury",
    "seeking_fury",
    "시킹 퓨리"
  ],
  "tags": [
    "mod",
    "primary",
    "rare",
    "shotgun"
  ],
  "game_ref": "/Lotus/Upgrades/Mods/Shotgun/DualStat/ReloadSpeedPunchThroughMod",
  "max_rank": 5,
  "tradable": true,
  "icon": "items/images/en/seeking_fury.bcb6c27bae6bd82cfd148825128415a6.png",
  "thumb": "items/images/en/thumbs/seeking_fury.bcb6c27bae6bd82cfd148825128415a6.128x128.png",
  "source": {
    "warframe_market_items": "https://api.warframe.market/v2/items"
  },
  "updated_at": "2026-06-28T15:19:32Z",
  "version": "26-06-29"
}