{
  "schema": "obs_prime.market_wiki_entry.v1",
  "market_id": "5ee76f4b04d55c0a81972435",
  "slug": "stahlta_set",
  "market_slug": "stahlta_set",
  "name_en": "Stahlta Set",
  "name_en_slug": "stahlta_set",
  "name_kr": "스탈타 세트",
  "aliases": [
    "Stahlta Set",
    "stahlta set",
    "stahlta_set",
    "스탈타 세트"
  ],
  "tags": [
    "primary",
    "set",
    "weapon"
  ],
  "game_ref": "/Lotus/Weapons/Corpus/LongGuns/CrpRubanRifle/CrpRubanRifle",
  "max_rank": null,
  "tradable": true,
  "icon": "items/images/en/stahlta_set.30d7537c3158976f86998e5b9fa05f96.png",
  "thumb": "items/images/en/thumbs/stahlta_set.30d7537c3158976f86998e5b9fa05f96.128x128.png",
  "source": {
    "warframe_market_items": "https://api.warframe.market/v2/items"
  },
  "updated_at": "2026-06-27T03:46:06Z",
  "version": "26-06-27"
}