{
  "schema": "obs_prime.market_wiki_entry.v1",
  "market_id": "5e839495267539077b0dd6cc",
  "slug": "titania_prime_blueprint",
  "market_slug": "titania_prime_blueprint",
  "name_en": "Titania Prime Blueprint",
  "name_en_slug": "titania_prime_blueprint",
  "name_kr": "티타니아 프라임 설계도",
  "aliases": [
    "Titania Prime",
    "Titania Prime Blueprint",
    "titania prime blueprint",
    "titania_prime_blueprint",
    "티타니아 프라임",
    "티타니아 프라임 설계도"
  ],
  "tags": [
    "blueprint",
    "prime",
    "warframe"
  ],
  "game_ref": "/Lotus/Types/Recipes/WarframeRecipes/TitaniaPrimeBlueprint",
  "max_rank": null,
  "tradable": true,
  "icon": "items/images/en/titania_prime_blueprint.d783da2b4926bc3760d50bba21eff7db.png",
  "thumb": "items/images/en/thumbs/titania_prime_blueprint.d783da2b4926bc3760d50bba21eff7db.128x128.png",
  "source": {
    "warframe_market_items": "https://api.warframe.market/v2/items"
  },
  "updated_at": "2026-06-28T15:19:32Z",
  "version": "26-06-29"
}