{
  "schema": "obs_prime.market_wiki_entry.v1",
  "market_id": "6054de7b5221e30057501082",
  "slug": "yogwun",
  "market_slug": "yogwun",
  "name_en": "Yogwun",
  "name_en_slug": "yogwun",
  "name_kr": "요그운",
  "aliases": [
    "Yogwun",
    "yogwun",
    "요그운"
  ],
  "tags": [
    "fish"
  ],
  "game_ref": "/Lotus/Types/Items/Fish/Eidolon/DayCommonFishCItem",
  "max_rank": null,
  "tradable": true,
  "icon": "items/images/en/yogwun.414590414a035d3f173860e662950d60.png",
  "thumb": "items/images/en/thumbs/yogwun.414590414a035d3f173860e662950d60.128x128.png",
  "source": {
    "warframe_market_items": "https://api.warframe.market/v2/items"
  },
  "updated_at": "2026-06-28T15:19:32Z",
  "version": "26-06-29"
}